<?xml version="1.0" encoding="utf-8"?>
<annotation>
	<folder></folder>
	<filename>2024-04-25_XRAISE_Person-hockend_80_00001515.jpg</filename>
	<path></path>
	<size>
		<width>1920</width>
		<height>1080</height>
		<depth>3</depth>
	</size>
	<segmented>0</segmented>
	<everythingAnnotated>partial</everythingAnnotated>
	<creation_date>2024-05-16</creation_date>
	<object>
		<classes>
			<name>person</name>
		</classes>
		<pose>Unspecified</pose>
		<difficult>0</difficult>
		<autoAnnotated>1</autoAnnotated>
		<level>4</level>
		<Nets>FcaNet-i5-4s_PBCMBTTnet-i5-0s_YOLOv5l_PeriPerzNet-i5-0m</Nets>
		<bndbox>
			<xmin>492</xmin>
			<ymin>323</ymin>
			<xmax>521</xmax>
			<ymax>417</ymax>
		</bndbox>
	</object>
	<object>
		<classes>
			<name>person</name>
		</classes>
		<pose>Unspecified</pose>
		<difficult>0</difficult>
		<autoAnnotated>1</autoAnnotated>
		<level>4</level>
		<Nets>FcaNet-i5-4s_PBCMBTTnet-i5-0s_PeriPerzNet-i5-0m_YOLOv5l</Nets>
		<bndbox>
			<xmin>448</xmin>
			<ymin>352</ymin>
			<xmax>498</xmax>
			<ymax>508</ymax>
		</bndbox>
	</object>
	<object>
		<classes>
			<name>person</name>
		</classes>
		<pose>Unspecified</pose>
		<difficult>0</difficult>
		<autoAnnotated>1</autoAnnotated>
		<level>2</level>
		<Nets>PeriPerzNet-i5-0m_YOLOv5l</Nets>
		<bndbox>
			<xmin>1548</xmin>
			<ymin>320</ymin>
			<xmax>1561</xmax>
			<ymax>350</ymax>
		</bndbox>
	</object>
	<unsure_objects>
		<classes>
			<name>person</name>
		</classes>
		<pose>Unspecified</pose>
		<difficult>0</difficult>
		<autoAnnotated>1</autoAnnotated>
		<level>1</level>
		<Nets>PeriPerzNet-i5-0m</Nets>
		<bndbox>
			<xmin>1572</xmin>
			<ymin>321</ymin>
			<xmax>1585</xmax>
			<ymax>353</ymax>
		</bndbox>
	</unsure_objects>
	<unsure_objects>
		<classes>
			<name>person</name>
		</classes>
		<pose>Unspecified</pose>
		<difficult>0</difficult>
		<autoAnnotated>1</autoAnnotated>
		<level>1</level>
		<Nets>PeriPerzNet-i5-0m</Nets>
		<bndbox>
			<xmin>291</xmin>
			<ymin>327</ymin>
			<xmax>308</xmax>
			<ymax>345</ymax>
		</bndbox>
	</unsure_objects>
</annotation>