[
  {
    "label": "person",
    "confidence": 0.8931767344474792,
    "bbox": [
      693,
      293,
      819,
      529
    ]
  },
  {
    "label": "person",
    "confidence": 0.5227013826370239,
    "bbox": [
      51,
      220,
      116,
      438
    ]
  },
  {
    "label": "person",
    "confidence": 0.41767698526382446,
    "bbox": [
      8,
      228,
      108,
      461
    ]
  },
  {
    "label": "person",
    "confidence": 0.31763365864753723,
    "bbox": [
      8,
      228,
      78,
      465
    ]
  }
]