[
  {
    "label": "person",
    "confidence": 0.6167872548103333,
    "bbox": [
      1590,
      257,
      1624,
      339
    ]
  },
  {
    "label": "person",
    "confidence": 0.5659486055374146,
    "bbox": [
      1651,
      253,
      1682,
      334
    ]
  },
  {
    "label": "person",
    "confidence": 0.5219348669052124,
    "bbox": [
      1723,
      259,
      1746,
      314
    ]
  },
  {
    "label": "person",
    "confidence": 0.39279553294181824,
    "bbox": [
      1737,
      276,
      1764,
      355
    ]
  },
  {
    "label": "person",
    "confidence": 0.37872472405433655,
    "bbox": [
      10,
      345,
      30,
      403
    ]
  },
  {
    "label": "person",
    "confidence": 0.3367438316345215,
    "bbox": [
      1723,
      260,
      1747,
      337
    ]
  }
]