[
  {
    "label": "person",
    "confidence": 0.9120041728019714,
    "bbox": [
      739,
      389,
      890,
      787
    ]
  },
  {
    "label": "person",
    "confidence": 0.891878604888916,
    "bbox": [
      555,
      358,
      656,
      610
    ]
  },
  {
    "label": "person",
    "confidence": 0.887450098991394,
    "bbox": [
      1120,
      363,
      1217,
      563
    ]
  },
  {
    "label": "person",
    "confidence": 0.8838653564453125,
    "bbox": [
      342,
      380,
      432,
      666
    ]
  },
  {
    "label": "person",
    "confidence": 0.8615987300872803,
    "bbox": [
      41,
      504,
      214,
      952
    ]
  },
  {
    "label": "person",
    "confidence": 0.7883898019790649,
    "bbox": [
      704,
      334,
      758,
      464
    ]
  },
  {
    "label": "person",
    "confidence": 0.7787014842033386,
    "bbox": [
      1252,
      335,
      1283,
      420
    ]
  },
  {
    "label": "person",
    "confidence": 0.3131738603115082,
    "bbox": [
      256,
      287,
      279,
      344
    ]
  }
]