[
  {
    "label": "person",
    "confidence": 0.8873581290245056,
    "bbox": [
      150,
      427,
      272,
      716
    ]
  },
  {
    "label": "person",
    "confidence": 0.8585038185119629,
    "bbox": [
      559,
      352,
      627,
      557
    ]
  },
  {
    "label": "person",
    "confidence": 0.8523643016815186,
    "bbox": [
      703,
      345,
      779,
      554
    ]
  },
  {
    "label": "person",
    "confidence": 0.805101752281189,
    "bbox": [
      1100,
      355,
      1180,
      525
    ]
  },
  {
    "label": "person",
    "confidence": 0.8045857548713684,
    "bbox": [
      908,
      342,
      1000,
      572
    ]
  },
  {
    "label": "person",
    "confidence": 0.6954194903373718,
    "bbox": [
      754,
      324,
      792,
      427
    ]
  },
  {
    "label": "person",
    "confidence": 0.5818276405334473,
    "bbox": [
      1146,
      325,
      1173,
      409
    ]
  },
  {
    "label": "person",
    "confidence": 0.36824512481689453,
    "bbox": [
      256,
      286,
      278,
      344
    ]
  }
]