[
  {
    "label": "person",
    "confidence": 0.8354861736297607,
    "bbox": [
      264,
      363,
      309,
      520
    ]
  },
  {
    "label": "person",
    "confidence": 0.7028743028640747,
    "bbox": [
      0,
      396,
      20,
      558
    ]
  },
  {
    "label": "person",
    "confidence": 0.661132276058197,
    "bbox": [
      533,
      328,
      567,
      426
    ]
  },
  {
    "label": "person",
    "confidence": 0.5180697441101074,
    "bbox": [
      820,
      393,
      836,
      433
    ]
  },
  {
    "label": "person",
    "confidence": 0.4656251072883606,
    "bbox": [
      702,
      321,
      744,
      425
    ]
  },
  {
    "label": "person",
    "confidence": 0.3589639961719513,
    "bbox": [
      552,
      328,
      572,
      404
    ]
  },
  {
    "label": "person",
    "confidence": 0.3396857678890228,
    "bbox": [
      715,
      318,
      752,
      425
    ]
  }
]