[
  {
    "label": "person",
    "confidence": 0.7983425855636597,
    "bbox": [
      1276,
      332,
      1311,
      430
    ]
  },
  {
    "label": "person",
    "confidence": 0.7970887422561646,
    "bbox": [
      1009,
      329,
      1044,
      420
    ]
  },
  {
    "label": "person",
    "confidence": 0.7570067048072815,
    "bbox": [
      1334,
      348,
      1372,
      446
    ]
  },
  {
    "label": "person",
    "confidence": 0.6936559677124023,
    "bbox": [
      1140,
      317,
      1165,
      388
    ]
  },
  {
    "label": "person",
    "confidence": 0.6927738785743713,
    "bbox": [
      1099,
      322,
      1141,
      449
    ]
  },
  {
    "label": "person",
    "confidence": 0.6883343458175659,
    "bbox": [
      937,
      309,
      967,
      381
    ]
  },
  {
    "label": "person",
    "confidence": 0.40823113918304443,
    "bbox": [
      969,
      314,
      999,
      387
    ]
  }
]