[
  {
    "label": "person",
    "confidence": 0.8576684594154358,
    "bbox": [
      1667,
      419,
      1767,
      743
    ]
  },
  {
    "label": "person",
    "confidence": 0.8447304964065552,
    "bbox": [
      1135,
      331,
      1190,
      474
    ]
  },
  {
    "label": "person",
    "confidence": 0.8234870433807373,
    "bbox": [
      1422,
      340,
      1465,
      461
    ]
  },
  {
    "label": "person",
    "confidence": 0.8227300047874451,
    "bbox": [
      1296,
      348,
      1361,
      539
    ]
  },
  {
    "label": "person",
    "confidence": 0.7394062280654907,
    "bbox": [
      1639,
      367,
      1680,
      528
    ]
  }
]