[
  {
    "label": "person",
    "confidence": 0.7849884033203125,
    "bbox": [
      672,
      205,
      696,
      277
    ]
  },
  {
    "label": "person",
    "confidence": 0.7848176956176758,
    "bbox": [
      593,
      208,
      619,
      285
    ]
  },
  {
    "label": "person",
    "confidence": 0.7665072679519653,
    "bbox": [
      626,
      204,
      657,
      282
    ]
  },
  {
    "label": "person",
    "confidence": 0.587666392326355,
    "bbox": [
      862,
      222,
      885,
      272
    ]
  }
]