[
  {
    "label": "person",
    "confidence": 0.8269096612930298,
    "bbox": [
      624,
      204,
      657,
      284
    ]
  },
  {
    "label": "person",
    "confidence": 0.7909616827964783,
    "bbox": [
      581,
      206,
      616,
      288
    ]
  },
  {
    "label": "person",
    "confidence": 0.7888079285621643,
    "bbox": [
      197,
      227,
      247,
      382
    ]
  },
  {
    "label": "person",
    "confidence": 0.7728753089904785,
    "bbox": [
      119,
      244,
      181,
      387
    ]
  },
  {
    "label": "person",
    "confidence": 0.7705836892127991,
    "bbox": [
      242,
      235,
      289,
      381
    ]
  }
]