[
  {
    "label": "person",
    "confidence": 0.7881025075912476,
    "bbox": [
      657,
      207,
      683,
      271
    ]
  },
  {
    "label": "person",
    "confidence": 0.7813368439674377,
    "bbox": [
      416,
      223,
      456,
      323
    ]
  },
  {
    "label": "person",
    "confidence": 0.7636134624481201,
    "bbox": [
      445,
      211,
      479,
      314
    ]
  },
  {
    "label": "person",
    "confidence": 0.7512887120246887,
    "bbox": [
      510,
      212,
      547,
      309
    ]
  },
  {
    "label": "person",
    "confidence": 0.725680947303772,
    "bbox": [
      1057,
      222,
      1078,
      277
    ]
  }
]