[
  {
    "label": "person",
    "confidence": 0.7363460063934326,
    "bbox": [
      822,
      202,
      849,
      256
    ]
  },
  {
    "label": "person",
    "confidence": 0.715466320514679,
    "bbox": [
      594,
      211,
      622,
      290
    ]
  },
  {
    "label": "person",
    "confidence": 0.6567947864532471,
    "bbox": [
      557,
      208,
      582,
      292
    ]
  },
  {
    "label": "person",
    "confidence": 0.6342059373855591,
    "bbox": [
      533,
      211,
      564,
      296
    ]
  },
  {
    "label": "person",
    "confidence": 0.5048685073852539,
    "bbox": [
      1376,
      242,
      1392,
      279
    ]
  },
  {
    "label": "person",
    "confidence": 0.30848291516304016,
    "bbox": [
      547,
      208,
      579,
      293
    ]
  }
]